{
  "auth": {
    "picxd4e835a7": {
      "service": "Cognito",
      "providerPlugin": "awscloudformation",
      "dependsOn": [],
      "customAuth": false,
      "frontendAuthConfig": {
        "socialProviders": [],
        "usernameAttributes": [],
        "signupAttributes": [
          "EMAIL"
        ],
        "passwordProtectionSettings": {
          "passwordPolicyMinLength": 8,
          "passwordPolicyCharacters": []
        },
        "mfaConfiguration": "OFF",
        "mfaTypes": [
          "SMS"
        ],
        "verificationMechanisms": [
          "EMAIL"
        ]
      }
    }
  },
  "api": {
    "picx": {
      "service": "AppSync",
      "providerPlugin": "awscloudformation",
      "dependsOn": [
        {
          "category": "auth",
          "resourceName": "picxd4e835a7",
          "attributes": [
            "UserPoolId"
          ]
        }
      ],
      "output": {
        "authConfig": {
          "defaultAuthentication": {
            "authenticationType": "API_KEY",
            "apiKeyConfig": {
              "apiKeyExpirationDays": 90,
              "apiKeyExpirationDate": "2022-07-30T21:33:07.696Z",
              "description": "graph api key"
            }
          },
          "additionalAuthenticationProviders": [
            {
              "authenticationType": "AMAZON_COGNITO_USER_POOLS",
              "userPoolConfig": {
                "userPoolId": "authpicxd4e835a7"
              }
            }
          ]
        }
      }
    }
  },
  "storage": {
    "imagesPicx": {
      "service": "S3",
      "providerPlugin": "awscloudformation",
      "dependsOn": []
    }
  }
}